EditableFlask/__init__.py
EditableFlask/conditions.py
EditableFlask/editable.py
EditableFlask/views.py
EditableFlask/assets/favicon.ico
EditableFlask/assets/script.js
EditableFlask/assets/style.css
EditableFlask/assets/bootstrap/css/bootstrap-theme.css
EditableFlask/assets/bootstrap/css/bootstrap-theme.css.map
EditableFlask/assets/bootstrap/css/bootstrap-theme.min.css
EditableFlask/assets/bootstrap/css/bootstrap.css
EditableFlask/assets/bootstrap/css/bootstrap.css.map
EditableFlask/assets/bootstrap/css/bootstrap.min.css
EditableFlask/assets/bootstrap/css/navbar.css
EditableFlask/assets/bootstrap/fonts/glyphicons-halflings-regular.eot
EditableFlask/assets/bootstrap/fonts/glyphicons-halflings-regular.svg
EditableFlask/assets/bootstrap/fonts/glyphicons-halflings-regular.ttf
EditableFlask/assets/bootstrap/fonts/glyphicons-halflings-regular.woff
EditableFlask/assets/bootstrap/js/bootstrap.js
EditableFlask/assets/bootstrap/js/bootstrap.min.js
EditableFlask/assets/bootstrap-switch/css/bootstrap-switch.min.css
EditableFlask/assets/bootstrap-switch/js/bootstrap-switch.min.js
EditableFlask/assets/summernote/summernote-bs3.css
EditableFlask/assets/summernote/summernote.css
EditableFlask/assets/summernote/summernote.min.js
EditableFlask/pyfiles/analytics.py
EditableFlask/pyfiles/database.py
EditableFlask/pyfiles/edits_locked.py
EditableFlask/pyfiles/edits_locked_sql.py
EditableFlask/pyfiles/resource_monitor.py
EditableFlask/pyfiles/static.py
EditableFlask/pyfiles/__pycache__/analytics.cpython-311.pyc
EditableFlask/pyfiles/__pycache__/database.cpython-311.pyc
EditableFlask/pyfiles/__pycache__/edits_locked_sql.cpython-311.pyc
EditableFlask/pyfiles/__pycache__/resource_monitor.cpython-311.pyc
EditableFlask/pyfiles/__pycache__/static.cpython-311.pyc
EditableFlask/templates/analytics.html
EditableFlask/templates/edits-admin.html
EditableFlask/templates/login.html
EditableFlask/templates/monitor.html
EditableFlask/templates/navbar.htm
EditableFlask/templates/static.html
editableflask-2.0.0.1.dist-info/licenses/LICENSE
editableflask-2.0.0.1.dist-info/METADATA
editableflask-2.0.0.1.dist-info/WHEEL
editableflask-2.0.0.1.dist-info/top_level.txt
editableflask-2.0.0.1.dist-info/RECORD
