Metadata-Version: 2.4
Name: EditableFlask
Version: 2.0.0.1
Summary: Addon to Flask to edit HTML content in a running app.
Home-page: https://github.com/YOUR_USERNAME/EditableFlask
Author: Mahir Shah
Author-email: mahir.shah.sd@gmail.com
License: MIT
Keywords: flask editable live edit
Classifier: Development Status :: 5 - Production/Stable
Classifier: License :: OSI Approved :: MIT License
Classifier: Programming Language :: Python :: 3
License-File: LICENSE
Requires-Dist: Flask
Requires-Dist: Flask-Login
Requires-Dist: Flask-SQLAlchemy
Requires-Dist: psutil
Dynamic: author
Dynamic: author-email
Dynamic: classifier
Dynamic: description
Dynamic: description-content-type
Dynamic: home-page
Dynamic: keywords
Dynamic: license
Dynamic: license-file
Dynamic: requires-dist
Dynamic: summary
